langchain_robocorp/__init__.py
langchain_robocorp/_common.py
langchain_robocorp/_prompts.py
langchain_robocorp/py.typed
langchain_robocorp/toolkits.py
gigachain_robocorp-0.0.10.dist-info/LICENSE
gigachain_robocorp-0.0.10.dist-info/METADATA
gigachain_robocorp-0.0.10.dist-info/WHEEL
gigachain_robocorp-0.0.10.dist-info/RECORD
